runit_database/__init__.py
runit_database/collection.py
runit_database/core.py
runit_database/document.py
runit_database/model.py
runit_database/test.py
runit_database-0.0.8.dist-info/LICENSE
runit_database-0.0.8.dist-info/METADATA
runit_database-0.0.8.dist-info/WHEEL
runit_database-0.0.8.dist-info/top_level.txt
runit_database-0.0.8.dist-info/RECORD
